pcu_language/__init__.py
pcu_language/pcu_language.py
pcu_language-1.3.dist-info/DESCRIPTION.rst
pcu_language-1.3.dist-info/LICENSE.txt
pcu_language-1.3.dist-info/METADATA
pcu_language-1.3.dist-info/RECORD
pcu_language-1.3.dist-info/WHEEL
pcu_language-1.3.dist-info/metadata.json
pcu_language-1.3.dist-info/top_level.txt
tests/__init__.py
tests/test_pcu_language.py
